odoo9_addon_runbot_skip_tests-9.0.1.0.0.99.dev2-py2.7-nspkg.pth
odoo9_addon_runbot_skip_tests-9.0.1.0.0.99.dev2.dist-info/METADATA
odoo9_addon_runbot_skip_tests-9.0.1.0.0.99.dev2.dist-info/RECORD
odoo9_addon_runbot_skip_tests-9.0.1.0.0.99.dev2.dist-info/WHEEL
odoo9_addon_runbot_skip_tests-9.0.1.0.0.99.dev2.dist-info/namespace_packages.txt
odoo9_addon_runbot_skip_tests-9.0.1.0.0.99.dev2.dist-info/top_level.txt
odoo_addons/runbot_skip_tests/README.rst
odoo_addons/runbot_skip_tests/__init__.py
odoo_addons/runbot_skip_tests/__openerp__.py
odoo_addons/runbot_skip_tests/models/__init__.py
odoo_addons/runbot_skip_tests/models/runbot_build.py
odoo_addons/runbot_skip_tests/static/description/icon.png
