Metadata-Version: 2.1
Name: odoo9-addon-runbot-skip-tests
Version: 9.0.1.0.0.99.dev2
Summary: Skip tests on runbot builds
Home-page: UNKNOWN
Author: Savoir-faire Linux,Odoo Community Association (OCA)
Author-email: support@odoo-community.org
License: AGPL-3
Platform: UNKNOWN
Classifier: Programming Language :: Python
Classifier: Framework :: Odoo
Classifier: License :: OSI Approved :: GNU Affero General Public License v3
Requires-Python: ~=2.7
Requires-Dist: odoo9-addon-runbot
Requires-Dist: odoo (<9.1a,>=9.0a)
